Workbook

Sheet Assumptions
B2: Apple Inc. DCF Assumptions
B5: Key assumptions used throughout the discounted cash flow valuation model
B8: Assumption | C8: Value | D8: Source
B9: 2026 Revenue ($B) | C9: 478.29B | D9: Analyst Concensus
B10: 2027 Revenye Growth | C10: 0.0567 | D10: Assumption
B11: 2028 Revenue Growth | C11: 0.055 | D11: Assumption
B12: 2029 Revenue Growth | C12: 0.053 | D12: Assumption
B13: 2030 Revenue Growth | C13: 0.051 | D13: Assumption
B14: 2031 Revenue Growth | C14: 0.0495 | D14: Assumption
B15: EBIT Margin | C15: 0.3264 | D15: Historical
B16: Tax Rate | C16: 0.21 | D16: US Corporate Tax
B17: WACC | C17: 0.08 | D17: Assumption
B18: Terminal Growth Rate | C18: 0.025 | D18: Assumption
B19: D&A Percent Revenue | C19: 0.026 | D19: Assumption
B20: CapEx % Revenue | C20: 0.028 | D20: Assumption
B21: ΔNWC % Revenue | C21: 0.005 | D21: Assumption
B22: Revenue projections beyond FY2026 are based on analyst consensus for FY2026 and assumptions of gradually declining long-term growth to reflect Apple's mature business model.

Sheet Forecasts
D2: Apple Inc. Revenue & Operating Forecast
D5: Five-year operating forecast based on analyst consensus and management assumptions.
B8: Revenue Forecast | G8: Projected Operating Income Statement
B9: Year | C9: Revenue ($B) | D9: Growth | G9: Year | H9: Revenue ($B) | I9: EBIT Margin | J9: EBIT ($B) | K9: Tax Rate | L9: NOPAT ($B)
B10: 2026E | C10: 478.29 | D10: - | G10: 2026E | H10: =Forecasts!C10 -> 478.29 | I10: =Assumptions!$C$15 -> 0.3264 | J10: =H10*I10 -> 156.11386 | K10: =Assumptions!$C$16 -> 0.21 | L10: =J10*(1-Assumptions!$C$16) -> 123.32995
B11: 2027E | C11: 505.4 | D11: =Assumptions!C10 -> 0.0567 | G11: 2027E | H11: =Forecasts!C11 -> 505.4 | I11: =Assumptions!$C$15 -> 0.3264 | J11: =H11*I11 -> 164.96256 | K11: =Assumptions!$C$16 -> 0.21 | L11: =J11*(1-Assumptions!$C$16) -> 130.32042
B12: 2028E | C12: 533.197 | D12: =Assumptions!C11 -> 0.055 | G12: 2028E | H12: =Forecasts!C12 -> 533.197 | I12: =Assumptions!$C$15 -> 0.3264 | J12: =H12*I12 -> 174.0355 | K12: =Assumptions!$C$16 -> 0.21 | L12: =J12*(1-Assumptions!$C$16) -> 137.48805
B13: 2029E | C13: 561.4596 | D13: =Assumptions!C12 -> 0.053 | G13: 2029E | H13: =Forecasts!C13 -> 561.4596 | I13: =Assumptions!$C$15 -> 0.3264 | J13: =H13*I13 -> 183.26041 | K13: =Assumptions!$C$16 -> 0.21 | L13: =J13*(1-Assumptions!$C$16) -> 144.77573
B14: 2030E | C14: 590.09446 | D14: =Assumptions!C13 -> 0.051 | G14: 2030E | H14: =Forecasts!C14 -> 590.09446 | I14: =Assumptions!$C$15 -> 0.3264 | J14: =H14*I14 -> 192.60683 | K14: =Assumptions!$C$16 -> 0.21 | L14: =J14*(1-Assumptions!$C$16) -> 152.1594
B15: 2031E | C15: 619.29968 | D15: =Assumptions!C14 -> 0.0495 | G15: 2031E | H15: =Forecasts!C15 -> 619.29968 | I15: =Assumptions!$C$15 -> 0.3264 | J15: =H15*I15 -> 202.13941 | K15: =Assumptions!$C$16 -> 0.21 | L15: =J15*(1-Assumptions!$C$16) -> 159.69014

Sheet Valuations
B2: Apple Inc. Discounted Cash Flow Valuation
B5: Enterprise value estimated using a five-year discounted cash flow model with a Gordon Growth terminal value.
B7: Apple Inc. (NASDAQ: AAPL) — Enterprise valuation using a five-year DCF model
B9: DCF Valuation Summary
B10: Item | C10: Value ($B)
B11: PV of Forecast FCF | C11: =SUM(Valuations!E31:E36) -> 628.14114
B12: PV of Terminal Value | C12: =Valuations!C53 -> 1824.5005
B13: Enterprise Value | C13: =C11+C12 -> 2452.6417
B14: Current Enterprise Value | C14: 4300
B15: Difference (%) | C15: =(C13-C14)/C14% -> -42.961822
B16: Conclusion | C16: =IF(C15<0,"Overvalued","Undervalued") -> Overvalued
B19: Free Cash Flow Schedule
B20: Year | C20: NOPAT ($B) | D20: D&A | E20: CapEx | F20: ΔNWC | G20: Free Cash Flow
B21: 2026E | C21: =Forecasts!L10 -> 123.32995 | D21: =Forecasts!C10*Assumptions!C19 -> 12.43554 | E21: =Forecasts!C10*Assumptions!C20 -> 13.39212 | F21: =Forecasts!C10*Assumptions!C21 -> 2.39145 | G21: =C21+D21-E21-F21 -> 119.98192
B22: 2027E | C22: =Forecasts!L11 -> 130.32042 | D22: =Forecasts!C11*Assumptions!C19 -> 13.1404 | E22: =Forecasts!C11*Assumptions!C20 -> 14.1512 | F22: =Forecasts!C11*Assumptions!C21 -> 2.527 | G22: =C22+D22-E22-F22 -> 126.78262
B23: 2028E | C23: =Forecasts!L12 -> 137.48805 | D23: =Forecasts!C12*Assumptions!C19 -> 13.863122 | E23: =Forecasts!C12*Assumptions!C20 -> 14.929516 | F23: =Forecasts!C12*Assumptions!C21 -> 2.665985 | G23: =C23+D23-E23-F23 -> 133.75567
B24: 2029E | C24: =Forecasts!L13 -> 144.77573 | D24: =Forecasts!C13*Assumptions!C19 -> 14.59795 | E24: =Forecasts!C13*Assumptions!C20 -> 15.720869 | F24: =Forecasts!C13*Assumptions!C21 -> 2.807298 | G24: =C24+D24-E24-F24 -> 140.84551
B25: 2030E | C25: =Forecasts!L14 -> 152.1594 | D25: =Forecasts!C14*Assumptions!C19 -> 15.342456 | E25: =Forecasts!C14*Assumptions!C20 -> 16.522645 | F25: =Forecasts!C14*Assumptions!C21 -> 2.9504723 | G25: =C25+D25-E25-F25 -> 148.02874
B26: 2031E | C26: =Forecasts!L15 -> 159.69014 | D26: =Forecasts!C15*Assumptions!C19 -> 16.101792 | E26: =Forecasts!C15*Assumptions!C20 -> 17.340391 | F26: =Forecasts!C15*Assumptions!C21 -> 3.0964984 | G26: =C26+D26-E26-F26 -> 155.35504
B29: Discounted Cash Flow valuation
B30: Year | C30: Free Cash Flow | D30: Discount Factor | E30: Present Value
B31: 2026E | C31: =Valuations!G21 -> 119.98192 | D31: =1/(1+Assumptions!$C$17)^1 -> 0.92592593 | E31: =C31*D31 -> 111.09437
B32: 2027E | C32: =Valuations!G22 -> 126.78262 | D32: =1/(1+Assumptions!$C$17)^2 -> 0.85733882 | E32: =C32*D32 -> 108.69566
B33: 2028E | C33: =Valuations!G23 -> 133.75567 | D33: =1/(1+Assumptions!$C$17)^3 -> 0.79383224 | E33: =C33*D33 -> 106.17956
B34: 2029E | C34: =Valuations!G24 -> 140.84551 | D34: =1/(1+Assumptions!$C$17)^4 -> 0.73502985 | E34: =C34*D34 -> 103.52565
B35: 2030E | C35: =Valuations!G25 -> 148.02874 | D35: =1/(1+Assumptions!$C$17)^5 -> 0.6805832 | E35: =C35*D35 -> 100.74587
B36: 2031E | C36: =Valuations!G26 -> 155.35504 | D36: =1/(1+Assumptions!$C$17)^6 -> 0.63016963 | E36: =C36*D36 -> 97.900027
B39: Enterprise Value Calculation
B40: Item | C40: Value ($B)
B41: PV of Forecast FCF | C41: 628.14
B42: PV of Terminal Value | C42: 1824.5
B43: Enterprise Value | C43: 2452.64
B46: Terminal Value
B47: Item | C47: Value
B48: 2031 Free Cash Flow | C48: =Valuations!G26 -> 155.35504
B49: Terminal Growth | C49: =Assumptions!$C$18 -> 0.025
B50: 2032 FCF | C50: =C48*(1+Assumptions!$C$18) -> 159.23892
B51: Terminal Value | C51: =C50/(Assumptions!$C$17-Assumptions!$C$18) -> 2895.253
B52: Discount Factor | C52: =Valuations!D36 -> 0.63016963
B53: Present value of TV | C53: =C51*C52 -> 1824.5005

Sheet Sensitivity Analysis
B2: Apple Inc. DCF Sensitivity Analysis
B5: Enterprise Value ($B) across WACC and Terminal Growth Rate assumptions.
D8: Terminal Growth
C9: =155.36*(1+K11)/(K10-K11) -> 2895.3455 | D9: 0.015 | E9: 0.02 | F9: 0.025 | G9: 0.03 | H9: 0.035 | J9: Sensitivity inputs
B10: WACC | C10: 0.07 | D10: 2867.1 | E10: 3169.34 | F10: 3538.76 | G10: 4000.52 | H10: 4594.22 | J10: WACC | K10: 0.08
C11: 0.075 | D11: 2628.17 | E11: 2881.22 | F11: 3184.88 | G11: 3556.02 | H11: 4019.94 | J11: Terminal Growth | K11: 0.025
C12: 0.08 | D12: 2426.01 | E12: 2641.12 | F12: 2895.35 | G12: 3200.42 | H12: 3573.28
C13: 0.085 | D13: 2252.72 | E13: 2437.96 | F13: 2654.07 | G13: 2909.47 | H13: 3215.95
C14: 0.09 | D14: 2102.54 | E14: 2263.82 | F14: 2449.91 | G14: 2667.01 | H14: 2923.59
B16: DCF Sensitivity analysis
B17: Enterprise value ($B) based on varying assumptions for WACC and terminal growth rate. The highlighted cell represents the base-case valuation.
